__init__.py
moredecimals.py
moredecimals-1.0.1.dist-info/LICENSE
moredecimals-1.0.1.dist-info/METADATA
moredecimals-1.0.1.dist-info/WHEEL
moredecimals-1.0.1.dist-info/top_level.txt
moredecimals-1.0.1.dist-info/RECORD
